{
    "shopInfo": {
      "id":"1",
      "name":"门店1",
      "address":"No. 18, Wantang Road, Xihu District, Hangzhou, Zhejiang, China",
      "clerk":[
        {"id":"2","name":"职员2","position":"员工","contact":"15868859587"},
        {"id":"4","name":"职员4","position":"员工","contact":"15868859587"},
        {"id":"3","name":"职员3","position":"员工","contact":"15868859587"},
        {"id":"1","name":"职员1","position":"店长","contact":"15868859587"},
        {"id":"5","name":"职员5","position":"员工","contact":"15868859587"}
      ]
    },
    "retCode": "200",
    "error":""
}